stone_color/__init__.py
stone_color/align.py
stone_color/color.py
stone_color/messages.py
stone_color/processbar.py
stone_color/spinner.py
stone_color/tables.py
stone_color-0.3.1.dist-info/LICENSE
stone_color-0.3.1.dist-info/METADATA
stone_color-0.3.1.dist-info/WHEEL
stone_color-0.3.1.dist-info/top_level.txt
stone_color-0.3.1.dist-info/RECORD
