Metadata-Version: 2.2
Name: stone_color
Version: 0.3.1
Summary: Text formatting, coloring and tables library
Author: aniko33
Keywords: color,cli,table,terminal-colors,ansi,rgb
License-File: LICENSE
Dynamic: author
Dynamic: description
Dynamic: keywords
Dynamic: summary
